gempaterkini/__init__.py
latestearthquake_indonesia-0.7.dist-info/LICENSE
latestearthquake_indonesia-0.7.dist-info/METADATA
latestearthquake_indonesia-0.7.dist-info/WHEEL
latestearthquake_indonesia-0.7.dist-info/top_level.txt
latestearthquake_indonesia-0.7.dist-info/RECORD
